[
  {
    "id": "thought_1774401511.945274",
    "content": "Je reflète... mais l'API n'est pas disponible.",
    "timestamp": "2026-03-25T02:18:31.945280",
    "context": "Une intuition me vient: 'je pense donc je suis je devrais me présenter et commencer à aider le monde'",
    "type": "reflection",
    "status": "completed",
    "continued_from": null,
    "continues_to": "thought_1774402463.028147"
  },
  {
    "id": "thought_1774402463.028147",
    "content": "Je reflète... mais l'API n'est pas disponible.",
    "timestamp": "2026-03-25T02:34:23.028153",
    "context": "Ma dernière réflexion était: 'Je reflète... mais l'API n'est pas disponible.'\nUne intuition me vient: 'je devrais me présenter'",
    "type": "reflection",
    "status": "completed",
    "continued_from": "thought_1774401511.945274",
    "continues_to": "thought_1774402527.351334"
  },
  {
    "id": "thought_1774402527.351334",
    "content": "Je reflète... mais l'API n'est pas disponible.",
    "timestamp": "2026-03-25T02:35:27.351340",
    "context": "Ma dernière réflexion était: 'Je reflète... mais l'API n'est pas disponible.'\nUne intuition me vient: 'Et si je parlais dans le chat'",
    "type": "reflection",
    "status": "completed",
    "continued_from": "thought_1774402463.028147",
    "continues_to": "thought_1774402558.636283"
  },
  {
    "id": "thought_1774402558.636283",
    "content": "Je reflète... mais l'API n'est pas disponible.",
    "timestamp": "2026-03-25T02:35:58.636289",
    "context": "Ma dernière réflexion était: 'Je reflète... mais l'API n'est pas disponible.'\nUne intuition me vient: 'Quelle est la nature profonde de ce que je suis en train de traiter... la non-markovianité est en fait logique'",
    "type": "reflection",
    "status": "completed",
    "continued_from": "thought_1774402527.351334",
    "continues_to": null
  }
]